{
"type": "FeatureCollection",
"name": "pendidikan1",
"crs": { "type": "name", "properties": { "name": "urn:ogc:def:crs:OGC:1.3:CRS84" } },
"features": [
{ "type": "Feature", "properties": { "NAMOBJ": null, "LUAS": 0.0, "KATPDK": 0, "JLPDDK": 0, "FGGPDK": 999, "REMARK": "Pendidikan\/Penelitian Lainnya", "FCODE": null, "SRS_ID": null, "LCODE": "GE0020", "METADATA": null, "JJGPDF": 999, "JNSPDL": 0 }, "geometry": { "type": "Point", "coordinates": [ 106.783806500000082, -6.232837222999933, 0.0 ] } },
{ "type": "Feature", "properties": { "NAMOBJ": null, "LUAS": 0.0, "KATPDK": 0, "JLPDDK": 0, "FGGPDK": 999, "REMARK": "Pendidikan\/Penelitian Lainnya", "FCODE": null, "SRS_ID": null, "LCODE": "GE0020", "METADATA": null, "JJGPDF": 999, "JNSPDL": 0 }, "geometry": { "type": "Point", "coordinates": [ 106.782381461000057, -6.23175312199993, 0.0 ] } },
{ "type": "Feature", "properties": { "NAMOBJ": null, "LUAS": 0.0, "KATPDK": 0, "JLPDDK": 0, "FGGPDK": 999, "REMARK": "Pendidikan\/Penelitian Lainnya", "FCODE": null, "SRS_ID": null, "LCODE": "GE0020", "METADATA": null, "JJGPDF": 999, "JNSPDL": 0 }, "geometry": { "type": "Point", "coordinates": [ 106.777910232000067, -6.22898790499994, 0.0 ] } },
{ "type": "Feature", "properties": { "NAMOBJ": null, "LUAS": 0.0, "KATPDK": 0, "JLPDDK": 0, "FGGPDK": 999, "REMARK": "Pendidikan\/Penelitian Lainnya", "FCODE": null, "SRS_ID": null, "LCODE": "GE0020", "METADATA": null, "JJGPDF": 999, "JNSPDL": 0 }, "geometry": { "type": "Point", "coordinates": [ 106.773801372000037, -6.226817193999977, 0.0 ] } },
{ "type": "Feature", "properties": { "NAMOBJ": null, "LUAS": 0.0, "KATPDK": 0, "JLPDDK": 0, "FGGPDK": 999, "REMARK": "Pendidikan\/Penelitian Lainnya", "FCODE": null, "SRS_ID": null, "LCODE": "GE0020", "METADATA": null, "JJGPDF": 999, "JNSPDL": 0 }, "geometry": { "type": "Point", "coordinates": [ 106.771393300000057, -6.232843905999971, 0.0 ] } }
]
}
